{
  "nocubessrparmory:advsrparmoryroot": {
    "criteria": {
      "advsrparmoryroot": "2024-03-12 04:06:29 +0000"
    },
    "done": true
  },
  "nocubessrpnests:advsrpnestsaddonroot": {
    "criteria": {
      "advsrpnestsaddonroot": "2024-03-12 04:06:29 +0000"
    },
    "done": true
  },
  "nocubessrpsurvival:advparasitesurvivalroot": {
    "criteria": {
      "advparasitesurvivalroot": "2024-03-12 04:06:29 +0000"
    },
    "done": true
  },
  "minecraft:adventure/adventuring_time": {
    "criteria": {
      "plains": "2024-03-12 04:06:28 +0000"
    },
    "done": false
  }
}